gcplogs/__init__.py
gcplogs/_version.py
gcplogs/bin.py
gcplogs/constants.py
gcplogs/core.py
gcplogs/exceptions.py
gcplogs/helpers.py
gcplogs-0.0.3.dist-info/AUTHORS
gcplogs-0.0.3.dist-info/LICENSE
gcplogs-0.0.3.dist-info/METADATA
gcplogs-0.0.3.dist-info/WHEEL
gcplogs-0.0.3.dist-info/entry_points.txt
gcplogs-0.0.3.dist-info/top_level.txt
gcplogs-0.0.3.dist-info/RECORD
